jaxflow/__init__.py
jaxflow/cli.py
jaxflow/transforms.py
jaxflow/viz.py
jaxflow/core/__init__.py
jaxflow/core/dataset.py
jaxflow/core/loader.py
jaxflow/core/pytree.py
jaxflow/core/sampler.py
jaxflow/integrations/__init__.py
jaxflow/integrations/flax_utils.py
jaxflow/integrations/hf_utils.py
jaxflow/integrations/optax_utils.py
jaxflow/utils/__init__.py
jaxflow/utils/config.py
jaxflow/utils/logging.py
jaxflow/utils/random.py
jaxflow/utils/timing.py
jaxflow_lib-0.1.0.dist-info/licenses/LICENSE
jaxflow_lib-0.1.0.dist-info/METADATA
jaxflow_lib-0.1.0.dist-info/WHEEL
jaxflow_lib-0.1.0.dist-info/top_level.txt
jaxflow_lib-0.1.0.dist-info/RECORD
