Metadata-Version: 2.4
Name: jaxflow-lib
Version: 0.1.0
Summary: High-performance, PyTree-native data loading and processing for JAX/Flax
Author-email: Prabhnoor Singh <prabhnoors093@gmail.com>
License: MIT
Project-URL: Homepage, https://github.com/prabhnoors12/jaxflow
Project-URL: Documentation, https://github.com/prabhnoors12/jaxflow#readme
Project-URL: Repository, https://github.com/prabhnoors12/jaxflow
Project-URL: Issues, https://github.com/prabhnoors12/jaxflow/issues
Keywords: jax,flax,dataloader,dataset,machine-learning,deep-learning,neural-networks,pytree,performance
Classifier: Development Status :: 3 - Alpha
Classifier: Intended Audience :: Developers
Classifier: Intended Audience :: Science/Research
Classifier: License :: OSI Approved :: MIT License
Classifier: Programming Language :: Python :: 3
Classifier: Programming Language :: Python :: 3.8
Classifier: Programming Language :: Python :: 3.9
Classifier: Programming Language :: Python :: 3.10
Classifier: Programming Language :: Python :: 3.11
Classifier: Programming Language :: Python :: 3.12
Classifier: Topic :: Scientific/Engineering
Classifier: Topic :: Scientific/Engineering :: Artificial Intelligence
Classifier: Topic :: Software Development :: Libraries :: Python Modules
Classifier: Operating System :: OS Independent
Requires-Python: >=3.8
License-File: LICENSE
Requires-Dist: jax>=0.4.0
Requires-Dist: flax>=0.7.0
Requires-Dist: numpy
Provides-Extra: dev
Requires-Dist: pytest>=7.0; extra == "dev"
Requires-Dist: black; extra == "dev"
Requires-Dist: isort; extra == "dev"
Requires-Dist: mypy; extra == "dev"
Requires-Dist: mkdocs; extra == "dev"
Provides-Extra: viz
Requires-Dist: matplotlib; extra == "viz"
Requires-Dist: seaborn; extra == "viz"
Provides-Extra: all
Requires-Dist: jaxflow[dev,viz]; extra == "all"
Dynamic: license-file
